christmas/Blogging.py
christmas/S_DateTime.py
christmas/__init__.py
christmas/commonCode.py
christmas/cprintfs.py
christmas/processBar.py
christmas/read_conf.py
christmas/server_info.py
christmas/Pyshell/RS_File.py
christmas/Pyshell/__init__.py
christmas/SameAsMATLAB/CoorTrans.py
christmas/SameAsMATLAB/__init__.py
christmas/SameAsMATLAB/calculatefuns.py
christmas/Standard/__init__.py
christmas/Standard/xr_attrs.py
christmas/mncPy/.gitignore
christmas/mncPy/LICENSE
christmas/mncPy/__init__.py
christmas/mncPy/common.py
christmas/mncPy/compress.py
christmas/mncPy/__pycache__/__init__.cpython-311.pyc
christmas/mncPy/__pycache__/__init__.cpython-312.pyc
christmas/pFVCOM/__init__.py
christmas/pFVCOM/fvcom_class.py
christmas/pFVCOM/fvcom_image.py
christmas/pFVCOM/fvcom_load.py
christmas/pFVCOM/fvcom_tools.py
christmas/pFVCOM/writeFile.py
christmas/tools/P_params.py
christmas/tools/__init__.py
christmas/tools/download_check.py
christmas/tools/geo_distance.py
christmas/tools/kml2shp.py
christmas/warningTools/__init__.py
baysalt_christmas-2.0.0.dist-info/METADATA
baysalt_christmas-2.0.0.dist-info/WHEEL
baysalt_christmas-2.0.0.dist-info/top_level.txt
baysalt_christmas-2.0.0.dist-info/RECORD
