Metadata-Version: 2.2
Name: baysalt_christmas
Version: 2.0.0
Summary: Some simple tools for Christmas
Author: Christmas
Author-email: 273519355@qq.com
Classifier: Programming Language :: Python :: 3
Classifier: License :: OSI Approved :: MIT License
Classifier: Operating System :: OS Independent
Requires-Python: >=3.6
Requires-Dist: numpy
Requires-Dist: netCDF4
Requires-Dist: xarray
Requires-Dist: colorlog
Requires-Dist: requests
Dynamic: author
Dynamic: author-email
Dynamic: classifier
Dynamic: description
Dynamic: description-content-type
Dynamic: requires-dist
Dynamic: requires-python
Dynamic: summary
